IO_prompting/__init__.py
IO_prompting/generation.py
IO_prompting/prompt.py
IO_prompting/update.py
examples/baseline_no_hypothesis_inference.py
examples/batched_learning_generation.py
examples/batched_learning_inference.py
examples/generation.py
examples/inference.py
examples/multi_hyp_inference.py
examples/pdf_preprocess.py
examples/union_generation.py
finetune/finetune_llama.py
hypogenic/LLM_cache.py
hypogenic/__init__.py
hypogenic/extract_label.py
hypogenic/logger_config.py
hypogenic/prompt.py
hypogenic/register.py
hypogenic/tasks.py
hypogenic/utils.py
hypogenic/LLM_wrapper/__init__.py
hypogenic/LLM_wrapper/base.py
hypogenic/LLM_wrapper/claude.py
hypogenic/LLM_wrapper/gpt.py
hypogenic/LLM_wrapper/local.py
hypogenic/LLM_wrapper/rate_limiter.py
hypogenic/LLM_wrapper/wrapper_utils.py
hypogenic/algorithm/README.md
hypogenic/algorithm/__init__.py
hypogenic/algorithm/replace.py
hypogenic/algorithm/summary_information.py
hypogenic/algorithm/generation/README.md
hypogenic/algorithm/generation/__init__.py
hypogenic/algorithm/generation/base.py
hypogenic/algorithm/generation/default.py
hypogenic/algorithm/generation/utils.py
hypogenic/algorithm/inference/__init__.py
hypogenic/algorithm/inference/base.py
hypogenic/algorithm/inference/default.py
hypogenic/algorithm/inference/filter_and_weight.py
hypogenic/algorithm/inference/one_step_adaptive.py
hypogenic/algorithm/inference/two_step_adaptive.py
hypogenic/algorithm/inference/upperbound.py
hypogenic/algorithm/update/README.md
hypogenic/algorithm/update/__init__.py
hypogenic/algorithm/update/base.py
hypogenic/algorithm/update/default.py
hypogenic/algorithm/update/sampling.py
hypogenic-0.3.5.dist-info/licenses/LICENSE
hypogenic_cmd/__init__.py
hypogenic_cmd/generation.py
hypogenic_cmd/inference.py
hypothesis_agent/__init__.py
hypothesis_agent/utils.py
hypothesis_agent/data_analysis_agent/__init__.py
hypothesis_agent/data_analysis_agent/generation.py
hypothesis_agent/data_analysis_agent/inference.py
hypothesis_agent/data_analysis_agent/prompt.py
hypogenic-0.3.5.dist-info/METADATA
hypogenic-0.3.5.dist-info/WHEEL
hypogenic-0.3.5.dist-info/entry_points.txt
hypogenic-0.3.5.dist-info/top_level.txt
hypogenic-0.3.5.dist-info/RECORD
