Metadata-Version: 2.4
Name: hypogenic
Version: 0.3.5
Summary: A package for generating and evaluating hypotheses.
Author: Haokun Liu, Mingxuan Li, Chenfei Yuan, Yangqiaoyu Zhou, Tejes Srivastava, Chenhao Tan
Maintainer-email: Haokun Liu <haokunliu@uchicago.edu>
License: MIT
Project-URL: Homepage, https://github.com/ChicagoHAI/hypothesis-generation
Project-URL: Repository, https://github.com/ChicagoHAI/hypothesis-generation
Project-URL: Issues, https://github.com/ChicagoHAI/hypothesis-generation/issues
Classifier: Development Status :: 4 - Beta
Classifier: Programming Language :: Python :: 3
Classifier: Operating System :: OS Independent
Requires-Python: >=3.10
License-File: LICENSE
Requires-Dist: numpy~=1.26.3
Requires-Dist: pandas~=2.1.4
Requires-Dist: datasets~=2.16.1
Requires-Dist: transformers~=4.45.1
Requires-Dist: scikit-learn~=1.3.0
Requires-Dist: matplotlib~=3.8.0
Requires-Dist: pyyaml~=6.0.1
Requires-Dist: openai~=1.40.3
Requires-Dist: anthropic~=0.32.0
Requires-Dist: pulp~=2.9.0
Requires-Dist: redis~=5.0.1
Requires-Dist: torch~=2.4.0
Requires-Dist: accelerate~=0.33.0
Requires-Dist: colorlog~=6.8.2
Requires-Dist: tqdm
Requires-Dist: beautifulsoup4~=4.7.1
Requires-Dist: boto3~=1.34.158
Requires-Dist: requests~=2.32.3
Requires-Dist: Flask~=1.0.2
Requires-Dist: lxml
Requires-Dist: python-magic~=0.4.18
Requires-Dist: latex2mathml~=2.16.2
Requires-Dist: itsdangerous~=2.0.1
Requires-Dist: httpx==0.27.2
Provides-Extra: dev
Requires-Dist: vllm~=0.6.2; extra == "dev"
Requires-Dist: vllm-flash-attn~=2.6.2; extra == "dev"
Dynamic: license-file
